icd/__init__.py
icd/icd_to_comorbidities.py
icd/long_to_short_transformation.py
icd/comorbidity_mappings/charlson10.json
icd/comorbidity_mappings/quan_elixhauser10.json
tests/__init__.py
tests/test_icd_to_comorbidities.py
tests/test_long_to_short_transformation.py
icd-0.1.3.dist-info/LICENSE.txt
icd-0.1.3.dist-info/METADATA
icd-0.1.3.dist-info/WHEEL
icd-0.1.3.dist-info/top_level.txt
icd-0.1.3.dist-info/RECORD
