Metadata-Version: 2.1
Name: icd
Version: 0.1.3
Summary: Tools for working with icd codes and comorbidities
Home-page: https://github.com/mark-hoffmann/icd
Author: Mark Hoffmann
Author-email: markkhoffmann@gmail.com
License: UNKNOWN
Platform: UNKNOWN
Classifier: Development Status :: 2 - Pre-Alpha
Classifier: Programming Language :: Python
Classifier: Programming Language :: Python :: 3
Classifier: Programming Language :: Python :: 3.4
Classifier: Programming Language :: Python :: 3.5
Requires-Dist: pandas
